stringle/__init__.py
stringle/replacer.py
stringle-0.2.1.dist-info/METADATA
stringle-0.2.1.dist-info/WHEEL
stringle-0.2.1.dist-info/licenses/LICENSE
stringle-0.2.1.dist-info/RECORD
